checklog_odoo/__init__.py
checklog_odoo/__main__.py
checklog_odoo/checklog.py
checklog_odoo/compat.py
checklog_odoo/config.py
checklog_odoo-1.0.dist-info/METADATA
checklog_odoo-1.0.dist-info/WHEEL
checklog_odoo-1.0.dist-info/entry_points.txt
checklog_odoo-1.0.dist-info/licenses/LICENSE.txt
checklog_odoo-1.0.dist-info/RECORD
