Metadata-Version: 2.3
Name: checklog-odoo
Version: 1.0
Summary: Check if an odoo log file contains error, with the possibility to ignore some errors based on regular expressions
Project-URL: Documentation, https://github.com/acsone/checklog-odoo#readme
Project-URL: Issues, https://github.com/acsone/checklog-odoo/issues
Project-URL: Source, https://github.com/acsone/checklog-odoo
Author-email: Stéphane Bidoul <stephane.bidoul@acsone.eu>, Benoit Aimont <benoit.aimont@acsone.eu>
License-Expression: MIT
License-File: LICENSE.txt
Classifier: Development Status :: 4 - Beta
Classifier: Programming Language :: Python
Classifier: Programming Language :: Python :: 3.7
Classifier: Programming Language :: Python :: 3.8
Classifier: Programming Language :: Python :: 3.9
Classifier: Programming Language :: Python :: 3.10
Classifier: Programming Language :: Python :: 3.11
Classifier: Programming Language :: Python :: 3.12
Classifier: Programming Language :: Python :: Implementation :: CPython
Classifier: Programming Language :: Python :: Implementation :: PyPy
Requires-Python: >=3.7
Requires-Dist: click
Requires-Dist: tomli; python_version < '3.11'
Provides-Extra: test
Requires-Dist: coverage[toml]; extra == 'test'
Requires-Dist: pytest; extra == 'test'
